admin_shuffle/.DS_Store
admin_shuffle/__init__.py
admin_shuffle/admin.py
admin_shuffle/apps.py
admin_shuffle/__pycache__/__init__.cpython-36.pyc
admin_shuffle/__pycache__/__init__.cpython-37.pyc
admin_shuffle/__pycache__/__init__.cpython-38.pyc
admin_shuffle/__pycache__/admin.cpython-36.pyc
admin_shuffle/__pycache__/admin.cpython-37.pyc
admin_shuffle/__pycache__/admin.cpython-38.pyc
admin_shuffle/__pycache__/models.cpython-38.pyc
admin_shuffle/templates/.DS_Store
admin_shuffle/templates/admin_shuffle/change_list.html
django_admin_shuffle-0.1.7.dist-info/LICENSE
django_admin_shuffle-0.1.7.dist-info/METADATA
django_admin_shuffle-0.1.7.dist-info/WHEEL
django_admin_shuffle-0.1.7.dist-info/top_level.txt
django_admin_shuffle-0.1.7.dist-info/RECORD
